mezcal/__init__.py
mezcal/config.py
mezcal/version.py
mezcal/blueprints/__init__.py
mezcal/blueprints/rest_api.py
mezcal/models/__init__.py
mezcal/models/helpers.py
mezcal/resource/__init__.py
mezcal/resource/helpers.py
tests/__init__.py
tests/resources/__init__.py
tests/resources/test_helpers.py
mexcalli-0.0.0.2.dev0.dist-info/METADATA
mexcalli-0.0.0.2.dev0.dist-info/WHEEL
mexcalli-0.0.0.2.dev0.dist-info/top_level.txt
mexcalli-0.0.0.2.dev0.dist-info/RECORD
