Metadata-Version: 2.1
Name: mexcalli
Version: 0.0.0.2.dev0
Summary: test-mexcalli
Home-page: https://github.com/cuenca-mx/smezcal
Author: Cuenca
Author-email: dev@cuenca.com
License: UNKNOWN
Platform: UNKNOWN
Classifier: Programming Language :: Python :: 3
Classifier: Programming Language :: Python :: 3.6
Classifier: Programming Language :: Python :: 3.7
Classifier: Programming Language :: Python :: 3.8
Classifier: License :: OSI Approved :: MIT License
Classifier: Operating System :: OS Independent
Requires-Python: >=3.6
Requires-Dist: chalice (<1.18.0,>=1.16.0)
Requires-Dist: sentry-sdk (<0.17.0,>=0.16.2)
Requires-Dist: cuenca-validations (<0.5,>=0.4)
Requires-Dist: blinker (<1.5,>=1.4)
Requires-Dist: boto3 (<1.15.0,>=1.14.42)
Requires-Dist: mongoengine (<0.21.0,>=0.20.0)
Requires-Dist: dnspython (<2.1.0,>=2.0.0)
Requires-Dist: sentry-chalice (<0.3.0dataclasses>=0.6,>=0.2.0) ; python_version < "3.7"
